woodml/__init__.py
woodml/cli.py
woodml/cost.py
woodml/formulas.py
woodml/parser.py
woodml/svg.py
woodml/types.py
woodml/units.py
woodml_parser-1.0.0.dist-info/METADATA
woodml_parser-1.0.0.dist-info/WHEEL
woodml_parser-1.0.0.dist-info/entry_points.txt
woodml_parser-1.0.0.dist-info/RECORD
