Metadata-Version: 2.4
Name: woodml-parser
Version: 1.0.0
Summary: Reference parser for WoodML woodworking markup language
Project-URL: Homepage, https://github.com/yourusername/woodml
Project-URL: Documentation, https://github.com/yourusername/woodml#readme
Project-URL: Repository, https://github.com/yourusername/woodml
License-Expression: MIT
Keywords: cut-list,joinery,markup,parser,woodml,woodworking
Classifier: Development Status :: 4 - Beta
Classifier: Intended Audience :: Developers
Classifier: License :: OSI Approved :: MIT License
Classifier: Programming Language :: Python :: 3
Classifier: Programming Language :: Python :: 3.10
Classifier: Programming Language :: Python :: 3.11
Classifier: Programming Language :: Python :: 3.12
Classifier: Topic :: Software Development :: Libraries :: Python Modules
Requires-Python: >=3.10
Requires-Dist: pyyaml>=6.0
Provides-Extra: dev
Requires-Dist: mypy>=1.0; extra == 'dev'
Requires-Dist: pytest-cov>=4.0; extra == 'dev'
Requires-Dist: pytest>=7.0; extra == 'dev'
Requires-Dist: ruff>=0.1.0; extra == 'dev'
